TranslationsClient-0.1.0.dist-info/DESCRIPTION.rst
TranslationsClient-0.1.0.dist-info/METADATA
TranslationsClient-0.1.0.dist-info/RECORD
TranslationsClient-0.1.0.dist-info/WHEEL
TranslationsClient-0.1.0.dist-info/metadata.json
TranslationsClient-0.1.0.dist-info/top_level.txt
translations_client/__init__.py
translations_client/client.py
