Metadata-Version: 2.0
Name: TranslationsClient
Version: 0.1.0
Summary: A translations service Python client
Home-page: https://github.com/GreenelyAB/TranslationsClient
Author: GreenelyAB
Author-email: info@greenely.com
License: MIT
Keywords: translation translations client internationalization
Platform: UNKNOWN
Classifier: Development Status :: 5 - Production/Stable
Classifier: Intended Audience :: Developers
Classifier: Topic :: Communications
Classifier: Topic :: Software Development :: Internationalization
Classifier: Topic :: Software Development :: Localization
Classifier: Topic :: Software Development :: Libraries
Classifier: Topic :: Text Processing
Classifier: License :: OSI Approved :: MIT License
Classifier: Programming Language :: Python :: 3.5
Requires-Dist: pyzmq (>=15.2.0)
